strala_core/__init__.py
strala_core/schemas/__init__.py
strala_core/schemas/base.py
strala_core/services/__init__.py
strala_core/utils/__init__.py
strala_core_infrastructure-0.1.0.dist-info/METADATA
strala_core_infrastructure-0.1.0.dist-info/WHEEL
strala_core_infrastructure-0.1.0.dist-info/licenses/LICENSE
strala_core_infrastructure-0.1.0.dist-info/RECORD
